rapidrsa/__init__.py
rapidrsa/rapidrsa.py
rapidrsa-1.0.0.dist-info/LICENSE
rapidrsa-1.0.0.dist-info/METADATA
rapidrsa-1.0.0.dist-info/WHEEL
rapidrsa-1.0.0.dist-info/top_level.txt
rapidrsa-1.0.0.dist-info/RECORD
